scspell/__init__.py
scspell/__main__.py
scspell/_corpus.py
scspell/_portable.py
scspell/_util.py
scspell/data/dictionary.txt
scspell3k-2.3.0.dist-info/licenses/COPYING.txt
scspell3k-2.3.0.dist-info/METADATA
scspell3k-2.3.0.dist-info/WHEEL
scspell3k-2.3.0.dist-info/entry_points.txt
scspell3k-2.3.0.dist-info/top_level.txt
scspell3k-2.3.0.dist-info/RECORD
