Metadata-Version: 2.4
Name: scspell3k
Version: 2.3.0
Summary: A conservative interactive spell checker for source code.
License-Expression: GPL-2.0-only
Project-URL: GitHub, https://github.com/myint/scspell
Classifier: Development Status :: 4 - Beta
Classifier: Environment :: Console
Classifier: Intended Audience :: Developers
Classifier: Operating System :: OS Independent
Classifier: Programming Language :: Python :: 2.7
Classifier: Programming Language :: Python :: 3.9
Classifier: Programming Language :: Python :: 3.10
Classifier: Programming Language :: Python :: 3.11
Classifier: Programming Language :: Python :: 3.12
Classifier: Programming Language :: Python :: 3.13
Classifier: Topic :: Software Development
Classifier: Topic :: Text Processing :: Linguistic
Classifier: Topic :: Utilities
License-File: COPYING.txt
Dynamic: license-file
